radish/__init__.py
radish/cli.py
radish/command.py
radish/differs.py
radish/executioners.py
radish/outputter.py
radish/path.py
radish/utils.py
radish_run-0.1.0.dist-info/DESCRIPTION.rst
radish_run-0.1.0.dist-info/METADATA
radish_run-0.1.0.dist-info/RECORD
radish_run-0.1.0.dist-info/WHEEL
radish_run-0.1.0.dist-info/entry_points.txt
radish_run-0.1.0.dist-info/metadata.json
radish_run-0.1.0.dist-info/top_level.txt
