Metadata-Version: 2.0
Name: radish-run
Version: 0.1.0
Summary: A task runner that understands version control
Home-page: https://github.com/gaqzi/radish/
Author: Björn Andersson
Author-email: ba@sanitarium.se
License: Beerware license
Platform: UNKNOWN
Classifier: Intended Audience :: Developers
Classifier: License :: OSI Approved :: MIT License
Classifier: Development Status :: 4 - Beta
Classifier: Operating System :: OS Independent
Classifier: Programming Language :: Python
Classifier: Programming Language :: Python :: 2
Classifier: Programming Language :: Python :: 2.7
Classifier: Programming Language :: Python :: 3
Classifier: Programming Language :: Python :: 3.3
Classifier: Programming Language :: Python :: 3.4
Classifier: Programming Language :: Python :: 3.5
Requires-Dist: docopts
Requires-Dist: path.py
Requires-Dist: pyyaml
Requires-Dist: six
